<?xml version="1.0" encoding="UTF-8"?>
<?xml-stylesheet title="Dictionary view" media="screen,tv,projection" href="../../../../scripts/gt_dictionary.css" type="text/css"?>
<?xml-stylesheet alternate="yes" title="Hierarchical view" media="screen,tv,projection" href="../../../../scripts/gt_dictionary_alt.css" type="text/css"?>
<!DOCTYPE r PUBLIC "-//DivvunGiellatekno//DTD Dictionaries//Multilingual"
"../../../../scripts/gt_dictionary.dtd">
<r>
   <e>
      <lg>
         <l pos="a">ahkásaš</l>
      </lg>
      <mg>
         <tg>
            <t pos="phrase_a">av en bestemt alder</t>
            <xg>
               <x>Gaskkohagaid Elle váillahii iežas ahkásaš nuoraid, muhto gilážis eai gávdnon dakkáraččat.</x>
               <xt>I blant savnet Elle ungdom på hennes egen alder, men i den lille bygda fantes det ikke slike.</xt>
            </xg>
         </tg>
      </mg>
   </e>
   <e>
      <lg>
         <l context="mánná" pos="a">boruheapme</l>
      </lg>
      <mg>
         <tg>
            <t pos="phrase_a">som ikke har matlyst</t>
            <xg>
               <x>Ánne lei leamaš boruheapme daid maŋemus áiggiid ja lei sakka ruoidnan.</x>
               <xt>Ánne hadde ikke hatt matlyst den siste tiden og var blitt meget mager.</xt>
            </xg>
         </tg>
      </mg>
   </e>
   <e>
      <lg>
         <l context="jávri" pos="a">botniheapme</l>
      </lg>
      <mg>
         <tg>
            <t pos="a">bunnløs</t>
            <xg>
               <x>Duon jávrri lávejit lohkat botniheapmin.</x>
               <xt>Det der vannet bruker folk å si er bunnløst.</xt>
            </xg>
         </tg>
      </mg>
   </e>
   <e>
      <lg>
         <l context="vástádus" pos="a">eahpesihkkar</l>
      </lg>
      <mg>
         <tg>
            <t pos="a">usikker</t>
         </tg>
      </mg>
   </e>
   <e>
      <lg>
         <l context="olmmoš" pos="a">eŋgelas</l>
      </lg>
      <mg>
         <tg>
            <t pos="a">engelsk</t>
            <xg>
               <x>Mu mielas lea váttis oahppat eŋgelas lávlagiid.</x>
               <xt>Jeg synes det er vanskelig å lære engelske sanger.</xt>
            </xg>
         </tg>
      </mg>
   </e>
   <e>
      <lg>
         <l context="miella" pos="a">geahppat</l>
      </lg>
      <mg>
         <tg>
            <t pos="a">lett</t>
            <xg>
               <x>Elle viegai geahppa lávkkiiguin dievá badjel áhku lusa.</x>
               <xt>Elle løp med lette steg over haugen til bestemor.</xt>
            </xg>
         </tg>
      </mg>
   </e>
   <e>
      <lg>
         <l context="bargi" pos="a">gráfalaš</l>
      </lg>
      <mg>
         <tg>
            <t pos="a">grafisk</t>
         </tg>
      </mg>
   </e>
   <e>
      <lg>
         <l context="olmmoš" pos="a">jurddašeaddji</l>
      </lg>
      <mg>
         <tg>
            <t pos="a">tenkende</t>
         </tg>
      </mg>
   </e>
   <e>
      <lg>
         <l context="musihkka" pos="a">klassihkalaš</l>
      </lg>
      <mg>
         <tg>
            <t pos="a">klassisk</t>
         </tg>
      </mg>
   </e>
   <e>
      <lg>
         <l context="borramuš" pos="a">lusttuheapme</l>
      </lg>
      <mg>
         <tg>
            <t pos="a">uappetittlig</t>
         </tg>
      </mg>
   </e>
   <e>
      <lg>
         <l context="olmmoš" pos="a">mánnálaš</l>
      </lg>
      <mg>
         <tg>
            <t pos="a">barnslig</t>
         </tg>
      </mg>
   </e>
   <e>
      <lg>
         <l context="geađgi" pos="a">njivllas</l>
      </lg>
      <mg>
         <tg>
            <t pos="a">slimete</t>
            <xg>
               <x>Várut! Dán jogas leat geađggit njivlasat.</x>
               <xt>Pass opp! I denne elva er steinene slimete.</xt>
            </xg>
         </tg>
      </mg>
   </e>
   <e>
      <lg>
         <l context="olmmoš" pos="a">normála</l>
      </lg>
      <mg>
         <tg>
            <t pos="a">normal</t>
         </tg>
      </mg>
   </e>
   <e>
      <lg>
         <l context="viessu" pos="a">oktonas</l>
      </lg>
      <mg>
         <tg>
            <t pos="a">alene</t>
            <xg>
               <x>Várrevielttis oidnen guhkás ja njárggas oidnojedje moadde oktonas viesu.</x>
               <xt>Fra fjellsiden så jeg langt og på neset skimtet jeg et par hus som sto alene.</xt>
            </xg>
         </tg>
      </mg>
   </e>
   <e>
      <lg>
         <l context="jietna" pos="a">roakkas</l>
      </lg>
      <mg>
         <tg>
            <re>om stemme</re>
            <t pos="a">dyp</t>
            <t pos="a">grov</t>
            <xg>
               <x>Mun čuovun du ruoktot! dajai Ánte roagga jienain.</x>
               <xt>Jeg følger deg hjem! sa Ánte med en grov stemme.</xt>
            </xg>
         </tg>
      </mg>
   </e>
   <e>
      <lg>
         <l context="mánná" pos="a">stađuheapme</l>
      </lg>
      <mg>
         <tg>
            <t pos="a">rastløs</t>
         </tg>
      </mg>
   </e>
   <e>
      <lg>
         <l context="bárdni" pos="a">tøffa</l>
      </lg>
      <mg>
         <tg>
            <t pos="a">tøff</t>
         </tg>
      </mg>
   </e>
   <e>
      <lg>
         <l context="olmmoš" pos="a">veahkkái</l>
      </lg>
      <mg>
         <tg>
            <t pos="a">hjelpsom</t>
            <xg>
               <x>Sárá lea hui veahkkái.</x>
               <xt>Sárá er veldig hjelpsom.</xt>
            </xg>
         </tg>
      </mg>
   </e>
</r>
