<?xml version="1.0" encoding="UTF-8"?>
<!DOCTYPE r
  PUBLIC "-//XMLmind//DTD smenob//SE" "../scripts/smenob.dtd">
<r>
   <e usage="ped" src="nj">
      <lg>
         <l pos="n">beassi</l>
         <lc>beasit</lc>
         <lc>besiid</lc>
      </lg>
      <mg>
         <tg>
            <t pos="n">reir</t>
            <xg>
               <x>Skire dagai beasi muorragierragii.</x>
               <xt>Skjæra lagde reir i trekrona.</xt>
            </xg>
            <xg>
               <x>Lottit eai leat vuos monnen buot besiide.</x>
               <xt>Fuglene har ikke ennå lagt egg i alle reirene.</xt>
            </xg>
         </tg>
      </mg>
      <mg>
         <tg>
            <t pos="f">never</t>
            <xg>
               <x>Mun gáikon beassi muoras cahkkehahkan.</x>
               <xt>Jeg flerret never av treet til opptenning.</xt>
            </xg>
         </tg>
      </mg>
   </e>
   <e usage="ped" src="nj">
      <lg>
         <l pos="n">gállu</l>
         <lc>gállut</lc>
      </lg>
      <mg>
         <tg>
            <t pos="f">panne</t>
            <xg>
               <x>Bivastat gálluid vihke lunttažat spáppa maŋis.</x>
               <xt>Med svette panner løp guttungene etter ballen.</xt>
            </xg>
         </tg>
      </mg>
      <mg>
         <tg>
            <t pos="n">kjølig vær</t>
            <xg>
               <x>Mannan geasi ledje guhkes gálut.</x>
               <xt>Siste sommer var det lenge kjølig vær.</xt>
            </xg>
         </tg>
      </mg>
   </e>
   <e src="nj">
      <lg>
         <l pos="n">duollu</l>
         <lc>duolu</lc>
         <lc>dullui</lc>
      </lg>
      <mg>
         <tg>
            <t pos="m">tele</t>
            <xg>
               <x>Eatnamis lea duollu go galbmo.</x>
            </xg>
            <xg>
               <x>Geainnus leat ollu rokkit duolu dihte.</x>
               <xt>I vegen er det mange hull på grunn av telen.</xt>
            </xg>
         </tg>
      </mg>
      <mg>
         <tg>
            <t pos="m">toll</t>
            <xg>
               <x>Eanandoalloministtar sáhttá vuolidit duollu.</x>
               <xt>Landbruksministeren kan sette ned tollen.</xt>
            </xg>
         </tg>
      </mg>
   </e>
   <e usage="ped">
      <lg>
         <l pos="n">dikšu</l>
      </lg>
      <mg>
         <tg>
            <t pos="f">pleie</t>
            <xg>
               <x>Eadni lea dan mađe buozas ahte dárbbaša divššu birra jándora.</x>
               <xt>Mor er såpass syk at hun trenger pleie døgnet rundt.</xt>
            </xg>
         </tg>
      </mg>
      <mg>
         <tg>
            <t pos="m">terapi</t>
            <xg>
               <x></x>
               <xt></xt>
            </xg>
         </tg>
      </mg>
      <mg>
         <tg>
            <t pos="m">pleier</t>
            <xg>
               <x>Ođđa ossodahkii dárbbašuvvojit goitge logi dikšu.</x>
               <xt>Til den nye avdelingen trenges iallfall 10 pleiere.</xt>
            </xg>
            <xg>
               <x>Sii háliidit buoridit bargodili erenomážit dikšuide.</x>
               <xt>De ønsker å forbedre arbeidsforholdene spesielt for pleierne.</xt>
            </xg>
         </tg>
      </mg>
   </e>
   <e src="nj">
      <lg>
         <l pos="n">dáhttu</l>
         <lc>dáhtut</lc>
      </lg>
      <mg>
         <tg>
            <t pos="n">ønske</t>
            <t pos="m">vilje</t>
            <xg>
               <x>Sámediggi galgá ovddastit sámi álbmoga dáhtu ja sámiid beroštumiid.</x>
               <xt>Sametinget skal representere det samiske folkets vilje og samenes interesser.</xt>
            </xg>
         </tg>
      </mg>
      <mg>
         <tg>
            <t pos="m">beder</t>
            <xg>
               <x> </x>
               <xt></xt>
            </xg>
         </tg>
      </mg>
   </e>
   <e src="nj">
      <lg>
         <l pos="n">borri</l>
         <lc>borit</lc>
      </lg>
      <mg>
         <tg>
            <t pos="m">kant</t>
            <xg>
               <x>njealje borrái</x>
               <xt>firkantet</xt>
            </xg>
         </tg>
      </mg>
      <mg>
         <tg>
            <t pos="m">ås</t>
            <xg>
               <x>Mearragáttis leat várrevilttiin dávjá borit.</x>
               <xt>På kysten er det ofte åser i fjellsidene.</xt>
            </xg>
         </tg>
      </mg>
      <mg>
         <tg>
            <t pos="m">spiser</t>
            <t pos="m">eter</t>
            <xg>
               <x>Dat olbmát ledje duhpatborrit, geaid lusa son bođii.</x>
               <xt>De karene var snustyggere, som han kom til.</xt>
            </xg>
             <xg>
               <x>Son háliidii báhčit duoid goaskimiid, boazoborriid.</x>
               <xt>Han/hun ville skyte de ørnene, reinspiserne.</xt>
            </xg>
        </tg>
      </mg>
      <mg>
         <tg>
            <t pos="n">uhyre</t>
            <xg>
               <x> </x>
               <xt></xt>
            </xg>
         </tg>
      </mg>
   </e>
   <e usage="ped">
      <lg>
         <l pos="n">gássa</l>
      </lg>
      <mg>
         <tg>
            <t pos="f">kasse</t>
         </tg>
      </mg>
      <mg>
         <tg>
            <t pos="f">gass</t>
             <xg>
               <x>Min biilavuoddji lei nu suorganan ahte ille šat nagoda duolmmastit gása.</x>
               <xt>Bilføreren vår var så forskrekket at han/hun knapt greide å trø på gassen.</xt>
            </xg>
             <xg>
               <x>Sii áigot fievrridit Snøhvit-guovllu gása olgoriikii.</x>
               <xt>De skal føre gassen fra Snøhvit til utlandet.</xt>
            </xg>
        </tg>
      </mg>
   </e>
   <e usage="ped" src="nj">
      <lg>
         <l pos="n">nisu</l>
         <lc>nissonat</lc>
      </lg>
      <mg>
         <tg>
            <t pos="f">kvinne</t>
            <xg>
               <x>Birrasiid 100 nissona ja dievddu oassálaste dán fierpmádatkonferánssas.</x>
               <xt>Rundt 100 kvinner og menn deltok i denne nettverkskonferansen.</xt>
            </xg>
            <xg>
               <x>Dán guovllus leat unnán bargosajit nissoniidda.</x>
               <xt>I dette området er det få arbeidsplasser for kvinner.</xt>
            </xg>
         </tg>
      </mg>
      <mg>
         <tg>
            <t pos="m">hvete</t>
            <xg>
               <x>Mun áiggun gilvit nisuid duon beldui.</x>
               <xt>Jeg skal så hvete i åkeren der borte.</xt>
            </xg>
         </tg>
      </mg>
   </e>
   <e usage="ped" src="nj">
      <lg>
         <l pos="n">vuovdi</l>
         <lc>vuovddit</lc>
         <lc>vuvddiid</lc>
      </lg>
      <mg>
         <tg>
            <t pos="m">skog</t>
            <xg>
               <x>Soai doamaiga vuovddi čađa dego sáhpánat sáhpánráigái.</x>
               <xt>De (to) skyndte seg gjennom skogen som mus til musehullet.</xt>
            </xg>
            <xg>
               <x>Son áibbašii Suoma suhkkes vuvddiide.</x>
               <xt>Han/hun lengtet til Finlands tette skoger.</xt>
            </xg>
         </tg>
      </mg>
      <mg>
         <tg>
            <t pos="m">selger</t>
            <xg>
               <x>Máŋga vuovdi ledje boahtán márkanii.</x>
               <xt>Mange selgere var kommet til markedet.</xt>
            </xg>
             <xg>
               <x>Mun dopmen máksit iežan velggiid buot vuovdiide.</x>
               <xt>Jeg skyndte meg å betale gjelda mi til alle selgerne.</xt>
            </xg>
        </tg>
      </mg>
   </e>
</r>