<?xml version="1.0" encoding="UTF-8"?>
<?xml-stylesheet type="text/css" href="../../scripts/gt_dictionary.css"?>
<!DOCTYPE r
  PUBLIC "-//XMLmind//DTD smenob//SE" "../../scripts/gt_staticdictionary.dtd">
<r>
  <e src="nj">
    <lg>
      <l pos="pron" type="recipr">guoibmáme</l>
         <analysis>Pron_Recipr_Du1_Acc</analysis>
         <analysis>Pron_Recipr_Du1_Gen</analysis>
         <mini_paradigm>
            <analysis ms="Pron_Recipr_Du1_Acc">
               <wordform>goabbat guoibmáme</wordform>
            </analysis>
            <analysis ms="Pron_Recipr_Du1_Gen">
               <wordform>goabbat guoibmáme</wordform>
            </analysis>
            <analysis ms="Pron_Recipr_Du1_Ill">
               <wordform>goabbat guoibmáseame</wordform>
            </analysis>
            <analysis ms="Pron_Recipr_Du1_Loc">
               <wordform>goabbat guoimmisteame</wordform>
            </analysis>
            <analysis ms="Pron_Recipr_Du1_Com">
               <wordform>goabbat guimmiineame</wordform>
            </analysis>
         </mini_paradigm>
    </lg>
    <mg>
      <tg>
        <t pos="pron">hverandre (vi to)</t>
	   <xg>
          <x>Moai dovde goabbat guoibmáme.</x>
          <xt>Vi (to) kjenner hverandre.</xt>
        </xg>   
      </tg>
    </mg>
  </e>
  <e src="nj">
    <lg>
      <l pos="pron" type="recipr">guoimmáde</l>
         <analysis>Pron_Recipr_Du2_Acc</analysis>
         <analysis>Pron_Recipr_Du2_Gen</analysis>
         <mini_paradigm>
            <analysis ms="Pron_Recipr_Du2_Acc">
               <wordform>goabbat guoimmáde</wordform>
            </analysis>
            <analysis ms="Pron_Recipr_Du2_Gen">
               <wordform>goabbat guoimmáde</wordform>
            </analysis>
            <analysis ms="Pron_Recipr_Du2_Ill">
               <wordform>goabbat guoibmáseatte</wordform>
            </analysis>
            <analysis ms="Pron_Recipr_Du2_Loc">
               <wordform>goabbat guoimmisteatte</wordform>
            </analysis>
            <analysis ms="Pron_Recipr_Du2_Com">
               <wordform>goabbat guimmiineatte</wordform>
            </analysis>
         </mini_paradigm>
    </lg>
    <mg>
      <tg>
        <t pos="pron">hverandre (dere to)</t>
	   <xg>
          <x>Doai dovdabeahtti goabbat guoimmáde.</x>
          <xt>Dere (to) kjenner hverandre.</xt>
        </xg>   
      </tg>
    </mg>
  </e>
  <e src="nj">
    <lg>
      <l pos="pron" type="recipr">guoimmiska</l>
         <analysis>Pron_Recipr_Du3_Acc</analysis>
         <analysis>Pron_Recipr_Du3_Gen</analysis>
         <mini_paradigm>
            <analysis ms="Pron_Recipr_Du3_Acc">
               <wordform>goabbat guoimmiska</wordform>
            </analysis>
            <analysis ms="Pron_Recipr_Du3_Gen">
               <wordform>goabbat guoimmiska</wordform>
            </analysis>
            <analysis ms="Pron_Recipr_Du3_Ill">
               <wordform>goabbat guoibmáseaskka</wordform>
            </analysis>
            <analysis ms="Pron_Recipr_Du3_Loc">
               <wordform>goabbat guoimmisteaskka</wordform>
            </analysis>
            <analysis ms="Pron_Recipr_Du3_Com">
               <wordform>goabbat guimmiineaskka</wordform>
            </analysis>
         </mini_paradigm>
    </lg>
    <mg>
      <tg>
        <t pos="pron">hverandre (de to)</t>
	   <xg>
          <x>Soai dovdaba goabbat guoimmiska.</x>
          <xt>De (to) kjenner hverandre.</xt>
        </xg>   
      </tg>
    </mg>
  </e>

  <e src="nj">
    <lg>
      <l pos="pron" type="recipr">guoibmámet</l>
         <analysis>Pron_Recipr_Pl1_Acc</analysis>
         <analysis>Pron_Recipr_Pl1_Gen</analysis>
         <mini_paradigm>
            <analysis ms="Pron_Recipr_Pl1_Acc">
               <wordform>guhtet guoibmámet</wordform>
            </analysis>
            <analysis ms="Pron_Recipr_Pl1_Gen">
               <wordform>guhtet guoibmámet</wordform>
            </analysis>
            <analysis ms="Pron_Recipr_Pl1_Ill">
               <wordform>guhtet guoibmáseamet</wordform>
            </analysis>
            <analysis ms="Pron_Recipr_Pl1_Loc">
               <wordform>guhtet guoimmisteamet</wordform>
            </analysis>
            <analysis ms="Pron_Recipr_Pl1_Com">
               <wordform>guhtet guimmiineamet</wordform>
            </analysis>
         </mini_paradigm>
    </lg>
    <mg>
      <tg>
        <t pos="pron">hverandre (vi - flere enn 2)</t>
	   <xg>
          <x>Mii dovdat guhtet guoibmámet.</x>
          <xt>Vi kjenner hverandre.</xt>
        </xg>   
      </tg>
    </mg>
  </e>
  <e src="nj">
    <lg>
      <l pos="pron" type="recipr">guimmiideamet</l>
         <analysis>Pron_Recipr_Pl1_Acc</analysis>
         <analysis>Pron_Recipr_Pl1_Gen</analysis>
         <mini_paradigm>
            <analysis ms="Pron_Recipr_Pl1_Acc">
               <wordform>guhtet guimmiideamet</wordform>
            </analysis>
            <analysis ms="Pron_Recipr_Pl1_Gen">
               <wordform>guhtet guimmiideamet</wordform>
            </analysis>
            <analysis ms="Pron_Recipr_Pl1_Ill">
               <wordform>guhtet guimmiidasamet</wordform>
            </analysis>
            <analysis ms="Pron_Recipr_Pl1_Loc">
               <wordform>guhtet guimmiineamet</wordform>
            </analysis>
            <analysis ms="Pron_Recipr_Pl1_Com">
               <wordform>guhtet guimmiideametguin</wordform>
            </analysis>
         </mini_paradigm>
    </lg>
    <mg>
      <tg>
        <t pos="pron">hverandre (vi - flere enn 2)</t>
	   <xg>
          <x>Mii dovdat guhtet guimmiideamet.</x>
          <xt>Vi kjenner hverandre.</xt>
        </xg>   
      </tg>
    </mg>
  </e>


  <e src="nj">
    <lg>
      <l pos="pron" type="recipr">guoimmádet</l>
         <analysis>Pron_Recipr_Pl2_Acc</analysis>
         <analysis>Pron_Recipr_Pl2_Gen</analysis>
         <mini_paradigm>
            <analysis ms="Pron_Recipr_Pl2_Acc">
               <wordform>guhtet guoimmádet</wordform>
            </analysis>
            <analysis ms="Pron_Recipr_Pl2_Gen">
               <wordform>guhtet guoimmádet</wordform>
            </analysis>
            <analysis ms="Pron_Recipr_Pl2_Ill">
               <wordform>guhtet guoibmáseattet</wordform>
            </analysis>
            <analysis ms="Pron_Recipr_Pl2_Loc">
               <wordform>guhtet guoimmisteattet</wordform>
            </analysis>
            <analysis ms="Pron_Recipr_Pl2_Com">
               <wordform>guhtet guimmiineattet</wordform>
            </analysis>
         </mini_paradigm>
    </lg>
    <mg>
      <tg>
        <t pos="pron">hverandre (dere - flere enn 2)</t>
	   <xg>
          <x>Dii dovdabehtet guhtet guoimmádet.</x>
          <xt>Dere kjenner hverandre.</xt>
        </xg>   
      </tg>
    </mg>
  </e>
  <e src="nj">
    <lg>
      <l pos="pron" type="recipr">guimmiideattet</l>
         <analysis>Pron_Recipr_Pl2_Acc</analysis>
         <analysis>Pron_Recipr_Pl2_Gen</analysis>
         <mini_paradigm>
            <analysis ms="Pron_Recipr_Pl2_Acc">
               <wordform>guhtet guimmiideattet</wordform>
            </analysis>
            <analysis ms="Pron_Recipr_Pl2_Gen">
               <wordform>guhtet guimmiideattet</wordform>
             </analysis>
           <analysis ms="Pron_Recipr_Pl2_Ill">
               <wordform>guhtet guimmiidasadet</wordform>
            </analysis>
            <analysis ms="Pron_Recipr_Pl2_Loc">
               <wordform>guhtet guimmiineattet</wordform>
            </analysis>
            <analysis ms="Pron_Recipr_Pl2_Com">
               <wordform>guhtet guimmiideattetguin</wordform>
            </analysis>
         </mini_paradigm>
    </lg>
    <mg>
      <tg>
        <t pos="pron">hverandre (dere - flere enn 2)</t>
	   <xg>
          <x>Dii dovdabehtet guhtet guimmiideattet.</x>
          <xt>Dere kjenner hverandre.</xt>
        </xg>   
      </tg>
    </mg>
  </e>

  <e src="nj">
    <lg>
      <l pos="pron" type="recipr">guoimmiset</l>
         <analysis>Pron_Recipr_Pl3_Acc</analysis>
         <analysis>Pron_Recipr_Pl3_Gen</analysis>
         <mini_paradigm>
            <analysis ms="Pron_Recipr_Pl3_Acc">
               <wordform>guhtet guoimmiset</wordform>
            </analysis>
            <analysis ms="Pron_Recipr_Pl3_Gen">
               <wordform>guhtet guoimmiset</wordform>
            </analysis>
            <analysis ms="Pron_Recipr_Pl3_Ill">
               <wordform>guhtet guoibmáseaset</wordform>
            </analysis>
            <analysis ms="Pron_Recipr_Pl3_Loc">
               <wordform>guhtet guoimmisteaset</wordform>
            </analysis>
            <analysis ms="Pron_Recipr_Pl3_Com">
               <wordform>guhtet guimmiineaset</wordform>
            </analysis>
         </mini_paradigm>
    </lg>
    <mg>
      <tg>
        <t pos="pron">hverandre (de - flere enn 2)</t>
	   <xg>
          <x>Sii dovdet guhtet guoimmiset.</x>
          <xt>De kjenner hverandre.</xt>
        </xg>   
      </tg>
    </mg>
  </e>
  <e src="nj">
    <lg>
      <l pos="pron" type="recipr">guimmiideaset</l>
         <analysis>Pron_Recipr_Pl3_Acc</analysis>
         <analysis>Pron_Recipr_Pl3_Gen</analysis>
         <mini_paradigm>
            <analysis ms="Pron_Recipr_Pl3_Acc">
               <wordform>guhtet guimmiideaset</wordform>
            </analysis>
            <analysis ms="Pron_Recipr_Pl3_Gen">
               <wordform>guhtet guimmiideaset</wordform>
            </analysis>
            <analysis ms="Pron_Recipr_Pl3_Ill">
               <wordform>guhtet guimmiidasaset</wordform>
            </analysis>
            <analysis ms="Pron_Recipr_Pl3_Loc">
               <wordform>guhtet guimmiineaset</wordform>
            </analysis>
            <analysis ms="Pron_Recipr_Pl3_Com">
               <wordform>guhtet guimmiideasetguin</wordform>
            </analysis>
         </mini_paradigm>
    </lg>
    <mg>
      <tg>
        <t pos="pron">hverandre (de - flere enn 2)</t>
	   <xg>
          <x>Sii dovdet guhtet guimmiideaset.</x>
          <xt>De kjenner hverandre.</xt>
        </xg>   
      </tg>
    </mg>
  </e>

  <e src="nj">
    <lg>
      <l pos="pron" type="recipr">nuppi</l>
         <analysis>Pron_Recipr_Du_Acc</analysis>
         <analysis>Pron_Recipr_Du_Gen</analysis>
         <mini_paradigm>
            <analysis ms="Pron_Recipr_Du_Acc">
               <wordform>nubbi nuppi</wordform>
            </analysis>
            <analysis ms="Pron_Recipr_Du_Gen">
               <wordform>nubbi nuppi</wordform>
            </analysis>
            <analysis ms="Pron_Recipr_Du_Ill">
               <wordform>nubbi nubbái</wordform>
            </analysis>
            <analysis ms="Pron_Recipr_Du_Loc">
               <wordform>nubbi nuppis</wordform>
            </analysis>
            <analysis ms="Pron_Recipr_Du_Com">
               <wordform>nubbi nuppiin</wordform>
            </analysis>
            <analysis ms="Pron_Recipr_Du_Ess">
               <wordform>nubbi nubbin</wordform>
            </analysis>
         </mini_paradigm>
    </lg>
    <mg>
      <tg>
        <t pos="pron">hverandre (om to)</t>
	   <xg>
          <x>Moai dovde nubbi nuppi.</x>
          <xt>Vi to kjenner hverandre.</xt>
        </xg>   
      </tg>
    </mg>
  </e>
  <e src="nj">
    <lg>
      <l pos="pron" type="recipr">nuppiid</l>
         <analysis>Pron_Recipr_Pl_Acc</analysis>
         <analysis>Pron_Recipr_Pl_Gen</analysis>
         <mini_paradigm>
            <analysis ms="Pron_Recipr_Pl_Acc">
               <wordform>nuppit nuppiid</wordform>
             </analysis>
           <analysis ms="Pron_Recipr_Pl_Gen">
               <wordform>nuppit nuppiid</wordform>
             </analysis>
           <analysis ms="Pron_Recipr_Pl_Ill">
               <wordform>nuppit nuppiide</wordform>
            </analysis>
            <analysis ms="Pron_Recipr_Pl_Loc">
               <wordform>nuppit nuppiin</wordform>
            </analysis>
            <analysis ms="Pron_Recipr_Pl_Com">
               <wordform>nuppit nuppiiguin</wordform>
            </analysis>
            <analysis ms="Pron_Recipr_Pl_Ess">
               <wordform>nuppit nubbin</wordform>
            </analysis>
         </mini_paradigm>
    </lg>
    <mg>
      <tg>
        <t pos="pron">hverandre (flere enn to)</t>
	   <xg>
          <x>Sii dovdet nuppit nuppiid.</x>
          <xt>De kjenner hverandre.</xt>
        </xg>   
      </tg>
    </mg>
  </e>


   <e>
      <lg>
         <l pos="pron" type="recipr">guoibmáseame</l>
         <lemma_ref lemmaID="guoibmáme_pron_recipr">guoibmáme</lemma_ref>
         <analysis>Pron_Recipr_Du1_Ill</analysis>
      </lg>
      <mg>
         <tg>
            <t pos="pron">til hverandre (vi to)</t>
	   <xg>
          <x>Moai muitaletne ságaid goabbat guoibmáseame.</x>
          <xt>Vi (to) forteller nytt til hverandre.</xt>
        </xg>   
         </tg>
      </mg>
   </e>
   <e>
      <lg>
         <l pos="pron" type="recipr">guoimmisteame</l>
         <lemma_ref lemmaID="guoibmáme_pron_recipr">guoibmáme</lemma_ref>
         <analysis>Pron_Recipr_Du1_Loc</analysis>
      </lg>
      <mg>
         <tg>
            <t pos="pron">hos hverandre (vi to)</t>
            <t pos="pron">fra hverandre (vi to)</t>
	   <xg>
          <x>Moai ožžo rávvagiid goabbat guoimmisteame.</x>
          <xt>Vi (to) får råd fra hverandre.</xt>
        </xg>   
         </tg>
      </mg>
   </e>
   <e>
      <lg>
         <l pos="pron" type="recipr">guimmiineame</l>
         <lemma_ref lemmaID="guoibmáme_pron_recipr">guoibmáme</lemma_ref>
         <analysis>Pron_Recipr_Du1_Com</analysis>
      </lg>
      <mg>
         <tg>
            <t pos="pron">med hverandre (vi to)</t>
	   <xg>
          <x>Moai leaikkastalle goabbat guimmiineame.</x>
          <xt>Vi (to) spøker med hverandre.</xt>
        </xg>   
         </tg>
      </mg>
   </e>
   <e>
      <lg>
         <l pos="pron" type="recipr">guoibmáseatte</l>
         <lemma_ref lemmaID="guoimmáde_pron_recipr">guoimmáde</lemma_ref>
         <analysis>Pron_Recipr_Du2_Ill</analysis>
      </lg>
      <mg>
         <tg>
            <t pos="pron">til hverandre (dere to)</t>
	   <xg>
          <x>Doai muitaleahppi ságaid goabbat guoibmáseatte.</x>
          <xt>Dere (to) forteller nytt til hverandre.</xt>
        </xg>   
         </tg>
      </mg>
   </e>
   <e>
      <lg>
         <l pos="pron" type="recipr">guoimmisteatte</l>
         <lemma_ref lemmaID="guoimmáde_pron_recipr">guoimmáde</lemma_ref>
         <analysis>Pron_Recipr_Du2_Loc</analysis>
      </lg>
      <mg>
         <tg>
            <t pos="pron">fra hverandre (dere to)</t>
	   <xg>
          <x>Doai oažžubeahtti rávvagiid goabbat guoimmisteatte.</x>
          <xt>Dere (to) får råd fra hverandre.</xt>
        </xg>   
         </tg>
      </mg>
   </e>
   <e>
      <lg>
         <l pos="pron" type="recipr">guimmiineatte</l>
         <lemma_ref lemmaID="guoimmáde_pron_recipr">guoimmáde</lemma_ref>
         <analysis>Pron_Recipr_Du2_Com</analysis>
      </lg>
      <mg>
         <tg>
            <t pos="pron">med hverandre (dere to)</t>
	   <xg>
          <x>Doai leaikkastallabeahtti goabbat guimmiineatte.</x>
          <xt>Dere (to) spøker med hverandre.</xt>
        </xg>   
         </tg>
      </mg>
   </e>
   <e>
      <lg>
         <l pos="pron" type="recipr">guoibmáseaskka</l>
         <lemma_ref lemmaID="guoimmiska_pron_recipr">guoimmiska</lemma_ref>
         <analysis>Pron_Recipr_Du3_Ill</analysis>
      </lg>
      <mg>
         <tg>
            <t pos="pron">til hverandre (de to)</t>
	   <xg>
          <x>Soai muitaleaba ságaid goabbat guoibmáseaskka.</x>
          <xt>De (to) forteller nytt til hverandre.</xt>
        </xg>   
         </tg>
      </mg>
   </e>
   <e>
      <lg>
         <l pos="pron" type="recipr">guoimmisteaskka</l>
         <lemma_ref lemmaID="guoimmiska_pron_recipr">guoimmiska</lemma_ref>
         <analysis>Pron_Recipr_Du3_Loc</analysis>
      </lg>
      <mg>
         <tg>
            <t pos="pron">hos hverandre (de to)</t>
            <t pos="pron">fra hverandre (de to)</t>
	   <xg>
          <x>Soai oažžuba rávvagiid goabbat guoimmisteaskka.</x>
          <xt>De (to) får råd fra hverandre.</xt>
        </xg>   
         </tg>
      </mg>
   </e>
   <e>
      <lg>
         <l pos="pron" type="recipr">guimmiineaskka</l>
         <lemma_ref lemmaID="guoimmiska_pron_recipr">guoimmiska</lemma_ref>
         <analysis>Pron_Recipr_Du3_Com</analysis>
      </lg>
      <mg>
         <tg>
            <t pos="pron">med hverandre (de to)</t>
	   <xg>
          <x>Soai leaikkastallaba goabbat guimmiineaskka.</x>
          <xt>De (to) spøker med hverandre.</xt>
        </xg>   
         </tg>
      </mg>
   </e>
   <e>
      <lg>
         <l pos="pron" type="recipr">guoibmáseamet</l>
         <lemma_ref lemmaID="guoibmámet_pron_recipr">guoibmámet</lemma_ref>
         <analysis>Pron_Recipr_Pl1_Ill</analysis>
      </lg>
      <mg>
         <tg>
            <t pos="pron">til hverandre (vi)</t>
	   <xg>
          <x>Mii muitalit ságaid guhtet guoibmáseamet.</x>
          <xt>Vi forteller nytt til hverandre.</xt>
        </xg>   
         </tg>
      </mg>
   </e>
   <e>
      <lg>
         <l pos="pron" type="recipr">guoimmisteamet</l>
         <lemma_ref lemmaID="guoibmámet_pron_recipr">guoibmámet</lemma_ref>
         <analysis>Pron_Recipr_Pl1_Loc</analysis>
      </lg>
      <mg>
         <tg>
            <t pos="pron">hos hverandre (vi)</t>
            <t pos="pron">fra hverandre (vi)</t>
	   <xg>
          <x>Mii oažžut rávvagiid guhtet guoimmisteamet.</x>
          <xt>Vi får råd fra hverandre.</xt>
        </xg>   
         </tg>
      </mg>
   </e>
   <e>
      <lg>
         <l pos="pron" type="recipr" nr="sg">guimmiineamet</l>
         <lemma_ref lemmaID="guoibmámet_pron_recipr">guoibmámet</lemma_ref>
         <analysis>Pron_Recipr_Pl1_Com</analysis>
      </lg>
      <mg>
         <tg>
            <t pos="pron">med hverandre (vi)</t>
	   <xg>
          <x>Mii leaikkastallat guhtet guimmiineamet.</x>
          <xt>Vi skøyer med hverandre.</xt>
        </xg>   
         </tg>
      </mg>
   </e>

   <e>
      <lg>
         <l pos="pron" type="recipr">guimmiidasamet</l>
         <lemma_ref lemmaID="guimmiideamet_pron_recipr">guimmiideamet</lemma_ref>
         <analysis>Pron_Recipr_Pl1_Ill</analysis>
      </lg>
      <mg>
         <tg>
            <t pos="pron">til hverandre (vi)</t>
	   <xg>
          <x>Mii muitalit ságaid guhtet guimmiidasamet.</x>
          <xt>Vi forteller nytt til hverandre.</xt>
        </xg>   
         </tg>
      </mg>
   </e>
   <e>
      <lg>
         <l pos="pron" type="recipr" nr="pl">guimmiineamet</l>
         <lemma_ref lemmaID="guimmiideamet_pron_recipr">guimmiideamet</lemma_ref>
         <analysis>Pron_Recipr_Pl1_Loc</analysis>
      </lg>
      <mg>
         <tg>
            <t pos="pron">hos hverandre (vi)</t>
            <t pos="pron">fra hverandre (vi)</t>
	   <xg>
          <x>Mii oažžut rávvagiid guhtet guimmiineamet.</x>
          <xt>Vi får råd fra hverandre.</xt>
        </xg>   
         </tg>
      </mg>
   </e>
   <e>
      <lg>
         <l pos="pron" type="recipr">guimmiideametguin</l>
         <lemma_ref lemmaID="guimmiideamet_pron_recipr">guimmiideamet</lemma_ref>
         <analysis>Pron_Recipr_Pl1_Com</analysis>
      </lg>
      <mg>
         <tg>
            <t pos="pron">med hverandre (vi)</t>
	   <xg>
          <x>Mii leaikkastallat guhtet guimmiideametguin.</x>
          <xt>Vi skøyer med hverandre.</xt>
        </xg>   
         </tg>
      </mg>
   </e>

   <e>
      <lg>
         <l pos="pron" type="recipr">guoibmáseattet</l>
         <lemma_ref lemmaID="guoimmádet_pron_recipr">guoimmádet</lemma_ref>
         <analysis>Pron_Recipr_Pl2_Ill</analysis>
      </lg>
      <mg>
         <tg>
            <t pos="pron">til hverandre (dere)</t>
	   <xg>
          <x>Dii muitalehpet ságaid guhtet guoibmáseattet.</x>
          <xt>Dere forteller nytt til hverandre.</xt>
        </xg>   
         </tg>
      </mg>
   </e>
   <e>
      <lg>
         <l pos="pron" type="recipr">guoimmisteattet</l>
         <lemma_ref lemmaID="guoimmádet_pron_recipr">guoimmádet</lemma_ref>
         <analysis>Pron_Recipr_Pl2_Loc</analysis>
      </lg>
      <mg>
         <tg>
            <t pos="pron">hos hverandre (dere)</t>
            <t pos="pron">fra hverandre (dere)</t>
	   <xg>
          <x>Dii oažžubehtet rávvagiid guhtet guoimmisteattet.</x>
          <xt>Dere får råd fra hverandre.</xt>
        </xg>   
         </tg>
      </mg>
   </e>
   <e>
      <lg>
         <l pos="pron" type="recipr" nr="sg">guimmiineattet</l>
         <lemma_ref lemmaID="guoimmádet_pron_recipr">guoimmádet</lemma_ref>
         <analysis>Pron_Recipr_Pl2_Com</analysis>
      </lg>
      <mg>
         <tg>
            <t pos="pron">med hverandre (dere)</t>
	   <xg>
          <x>Dii leaikkastallabehtet guhtet guimmiineattet.</x>
          <xt>Dere skøyer med hverandre.</xt>
        </xg>   
         </tg>
      </mg>
   </e>

   <e>
      <lg>
         <l pos="pron" type="recipr">guimmiidasadet</l>
         <lemma_ref lemmaID="guimmiideattet_pron_recipr">guimmiideattet</lemma_ref>
         <analysis>Pron_Recipr_Pl2_Ill</analysis>
      </lg>
      <mg>
         <tg>
            <t pos="pron">til hverandre (dere)</t>
	   <xg>
          <x>Dii muitalehpet ságaid guhtet guimmiidasadet.</x>
          <xt>Dere forteller nytt til hverandre.</xt>
        </xg>   
         </tg>
      </mg>
   </e>
   <e>
      <lg>
         <l pos="pron" type="recipr" nr="pl">guimmiineattet</l>
         <lemma_ref lemmaID="guimmiideattet_pron_recipr">guimmiideattet</lemma_ref>
         <analysis>Pron_Recipr_Pl2_Loc</analysis>
      </lg>
      <mg>
         <tg>
            <t pos="pron">hos hverandre (dere)</t>
            <t pos="pron">fra hverandre (dere)</t>
	   <xg>
          <x>Dii oažžubehtet rávvagiid guhtet guimmiineattet.</x>
          <xt>Dere får råd fra hverandre.</xt>
        </xg>   
         </tg>
      </mg>
   </e>
   <e>
      <lg>
         <l pos="pron" type="recipr">guimmiideattetguin</l>
         <lemma_ref lemmaID="guimmiideattet_pron_recipr">guimmiideattet</lemma_ref>
         <analysis>Pron_Recipr_Pl2_Com</analysis>
      </lg>
      <mg>
         <tg>
            <t pos="pron">med hverandre (dere)</t>
	   <xg>
          <x>Dii leaikkastallabehtet guhtet guimmiideattetguin.</x>
          <xt>Dere skøyer med hverandre.</xt>
        </xg>   
         </tg>
      </mg>
   </e>

   <e>
      <lg>
         <l pos="pron" type="recipr">guoibmáseaset</l>
         <lemma_ref lemmaID="guoimmiset_pron_recipr">guoimmiset</lemma_ref>
         <analysis>Pron_Recipr_Pl3_Ill</analysis>
      </lg>
      <mg>
         <tg>
            <t pos="pron">til hverandre (de)</t>
	   <xg>
          <x>Sii muitalit ságaid guhtet guoibmáseaset.</x>
          <xt>De forteller nytt til hverandre.</xt>
        </xg>   
         </tg>
      </mg>
   </e>
   <e>
      <lg>
         <l pos="pron" type="recipr">guoimmisteaset</l>
         <lemma_ref lemmaID="guoimmiset_pron_recipr">guoimmiset</lemma_ref>
         <analysis>Pron_Recipr_Pl3_Loc</analysis>
      </lg>
      <mg>
         <tg>
            <t pos="pron">hos hverandre (de)</t>
            <t pos="pron">fra hverandre (de)</t>
	   <xg>
          <x>Sii ožžot rávvagiid guhtet guoimmisteaset.</x>
          <xt>De får råd fra hverandre.</xt>
        </xg>   
         </tg>
      </mg>
   </e>
   <e>
      <lg>
         <l pos="pron" type="recipr" nr="sg">guimmiineaset</l>
         <lemma_ref lemmaID="guoimmiset_pron_recipr">guoimmiset</lemma_ref>
         <analysis>Pron_Recipr_Pl3_Com</analysis>
      </lg>
      <mg>
         <tg>
            <t pos="pron">med hverandre (de)</t>
	   <xg>
          <x>Sii leaikkastallet guhtet guimmiineaset.</x>
          <xt>De skøyer med hverandre.</xt>
        </xg>   
         </tg>
      </mg>
   </e>

   <e>
      <lg>
         <l pos="pron" type="recipr">guimmiidasaset</l>
         <lemma_ref lemmaID="guimmiideaset_pron_recipr">guimmiideaset</lemma_ref>
         <analysis>Pron_Recipr_Pl3_Ill</analysis>
      </lg>
      <mg>
         <tg>
            <t pos="pron">til hverandre (de)</t>
	   <xg>
          <x>Sii muitalit ságaid guhtet guimmiidasaset.</x>
          <xt>De forteller nytt til hverandre.</xt>
        </xg>   
         </tg>
      </mg>
   </e>
   <e>
      <lg>
         <l pos="pron" type="recipr" nr="pl">guimmiineaset</l>
         <lemma_ref lemmaID="guimmiideaset_pron_recipr">guimmiideaset</lemma_ref>
         <analysis>Pron_Recipr_Pl3_Loc</analysis>
      </lg>
      <mg>
         <tg>
            <t pos="pron">hos hverandre (de)</t>
            <t pos="pron">fra hverandre (de)</t>
	   <xg>
          <x>Sii ožžot rávvagiid guhtet guimmiineaset.</x>
          <xt>De får råd fra hverandre.</xt>
        </xg>   
         </tg>
      </mg>
   </e>
   <e>
      <lg>
         <l pos="pron" type="recipr">guimmiideasetguin</l>
         <lemma_ref lemmaID="guimmiideaset_pron_recipr">guimmiideaset</lemma_ref>
         <analysis>Pron_Recipr_Pl3_Com</analysis>
      </lg>
      <mg>
         <tg>
            <t pos="pron">med hverandre (de)</t>
	   <xg>
          <x>Sii leaikkastallet guhtet guimmiideasetguin.</x>
          <xt>De skøyer med hverandre.</xt>
        </xg>   
         </tg>
      </mg>
   </e>
   <e>
      <lg>
         <l pos="pron" type="recipr">nubbái</l>
         <lemma_ref lemmaID="nuppi_pron_recipr">nuppi</lemma_ref>
         <analysis>Pron_Recipr_Du_Ill</analysis>
      </lg>
      <mg>
         <tg>
            <t pos="pron">til hverandre (om to)</t>
	   <xg>
          <x>Soai muitaleaba ságaid nubbi nubbái.</x>
          <xt>De to forteller nytt til hverandre.</xt>
        </xg>   
         </tg>
      </mg>
   </e>
   <e>
      <lg>
         <l pos="pron" type="recipr">nuppis</l>
         <lemma_ref lemmaID="nuppi_pron_recipr">nuppi</lemma_ref>
         <analysis>Pron_Recipr_Du_Loc</analysis>
      </lg>
      <mg>
         <tg>
            <t pos="pron">hos hverandre (om to)</t>
            <t pos="pron">fra hverandre (om to)</t>
	   <xg>
          <x>Soai oažžuba rávvagiid nubbi nuppis.</x>
          <xt>De to får råd fra hverandre.</xt>
        </xg>   
         </tg>
      </mg>
   </e>
   <e>
      <lg>
         <l pos="pron" type="recipr" nr="sg">nuppiin</l>
         <lemma_ref lemmaID="nuppi_pron_recipr">nuppi</lemma_ref>
         <analysis>Pron_Recipr_Du_Com</analysis>
      </lg>
      <mg>
         <tg>
            <t pos="pron">med hverandre (om to)</t>
	   <xg>
          <x>Soai leaikastallaba nubbi nuppiin.</x>
          <xt>De to spøker med hverandre.</xt>
        </xg>   
         </tg>
      </mg>
   </e>
   <e>
      <lg>
         <l pos="pron" type="recipr" nr="du">nubbin</l>
         <lemma_ref lemmaID="nuppi_pron_recipr">nuppi</lemma_ref>
         <analysis>Pron_Recipr_Du_Ess</analysis>
      </lg>
      <mg>
         <tg>
            <t pos="pron">som hverandre (om to)</t> 
	   <xg>
          <x>Soai loggiiga sisa nubbi nubbin.</x>
          <xt>De to logget inn som hverandre.</xt>
        </xg>   
         </tg>
      </mg>
   </e>
   <e>
      <lg>
         <l pos="pron" type="recipr">nuppiide</l>
         <lemma_ref lemmaID="nuppiid_pron_recipr">nuppiid</lemma_ref>
         <analysis>Pron_Recipr_Pl_Ill</analysis>
      </lg>
      <mg>
         <tg>
            <t pos="pron">til hverandre (om flere enn to)</t>
	   <xg>
          <x>Sii muitalit ságaid nuppit nuppiide.</x>
          <xt>De forteller nytt til hverandre.</xt>
        </xg>   
         </tg>
      </mg>
   </e>
   <e>
      <lg>
         <l pos="pron" type="recipr" nr="pl">nuppiin</l>
         <lemma_ref lemmaID="nuppiid_pron_recipr">nuppiid</lemma_ref>
         <analysis>Pron_Recipr_Pl_Loc</analysis>
      </lg>
      <mg>
         <tg>
            <t pos="pron">hos hverandre (om flere enn to)</t>
            <t pos="pron">fra hverandre (om flere enn to)</t>
	   <xg>
          <x>Mii oažžut rávvagiid nuppit nuppiin.</x>
          <xt>Vi får råd fra hverandre.</xt>
        </xg>   
         </tg>
      </mg>
   </e>
   <e>
      <lg>
         <l pos="pron" type="recipr">nuppiiguin</l>
         <lemma_ref lemmaID="nuppiid_pron_recipr">nuppiid</lemma_ref>
         <analysis>Pron_Recipr_Pl_Com</analysis>
      </lg>
      <mg>
         <tg>
            <t pos="pron">med hverandre (om flere enn to)</t>
	   <xg>
          <x>Dii leaikastallabehtet nuppit nuppiiguin.</x>
          <xt>Dere spøker med hverandre.</xt>
        </xg>   
         </tg>
      </mg>
   </e>
   <e>
      <lg>
         <l pos="pron" type="recipr" nr="pl">nubbin</l>
         <lemma_ref lemmaID="nuppiid_pron_recipr">nuppiid</lemma_ref>
         <analysis>Pron_Recipr_Pl_Ess</analysis>
      </lg>
      <mg>
         <tg>
            <t pos="pron">som hverandre (om flere enn to)</t>
            <xg>
          <x>Sii loggejedje sisa nubbi nubbin.</x>
          <xt>De logget inn som hverandre.</xt>
        </xg>  
        </tg>
      </mg>
   </e>

</r>
