<?xml version="1.0" encoding="UTF-8"?>
<!DOCTYPE r PUBLIC "-//XMLmind//DTD smenob//SE"
"../scripts/smenob.dtd">
<r>
  <e src="nj">
    <lg>
      <l pos="pron">goabbat guoibmáme</l>
         <analysis>Pron_Recipr_Du1_Acc</analysis>
         <analysis>Pron_Recipr_Du1_Gen</analysis>
         <mini_paradigm>
            <analysis ms="Pron_Recipr_Du1_Ill">
               <wordform>goabbat guoibmáseame</wordform>
            </analysis>
            <analysis ms="Pron_Recipr_Du1_Loc">
               <wordform>goabbat guoimmisteame</wordform>
            </analysis>
            <analysis ms="Pron_Recipr_Du1_Com">
               <wordform>goabbat guimmiineame</wordform>
            </analysis>
         </mini_paradigm>
    </lg>
    <mg>
      <tg>
        <t pos="pron">hverandre (vi to)</t>
	   <xg>
          <x>moai dovde goabbat guoibmáme</x>
          <xt>vi (to) kjenner hverandre</xt>
        </xg>   
      </tg>
    </mg>
  </e>
  <e src="nj">
    <lg>
      <l pos="pron">goabbat guoimmáde</l>
         <analysis>Pron_Recipr_Du2_Acc</analysis>
         <analysis>Pron_Recipr_Du2_Gen</analysis>
         <mini_paradigm>
            <analysis ms="Pron_Recipr_Du2_Ill">
               <wordform>goabbat guoibmáseatte</wordform>
            </analysis>
            <analysis ms="Pron_Recipr_Du2_Loc">
               <wordform>goabbat guoimmisteatte</wordform>
            </analysis>
            <analysis ms="Pron_Recipr_Du2_Com">
               <wordform>goabbat guimmiineatte</wordform>
            </analysis>
         </mini_paradigm>
    </lg>
    <mg>
      <tg>
        <t pos="pron">hverandre (dere to)</t>
	   <xg>
          <x>doai dovdabeahtti goabbat guoimmáde</x>
          <xt>dere (to) kjenner hverandre</xt>
        </xg>   
      </tg>
    </mg>
  </e>
  <e src="nj">
    <lg>
      <l pos="pron">goabbat guoimmiska</l>
         <analysis>Pron_Recipr_Du3_Acc</analysis>
         <analysis>Pron_Recipr_Du3_Gen</analysis>
         <mini_paradigm>
            <analysis ms="Pron_Recipr_Du3_Ill">
               <wordform>goabbat guoibmáseaskka</wordform>
            </analysis>
            <analysis ms="Pron_Recipr_Du3_Loc">
               <wordform>goabbat guoimmisteaskka</wordform>
            </analysis>
            <analysis ms="Pron_Recipr_Du3_Com">
               <wordform>goabbat guimmiineaskka</wordform>
            </analysis>
         </mini_paradigm>
    </lg>
    <mg>
      <tg>
        <t pos="pron">hverandre (de to)</t>
	   <xg>
          <x>soai dovdaba goabbat guoimmiska</x>
          <xt>de (to) kjenner hverandre</xt>
        </xg>   
      </tg>
    </mg>
  </e>

  <e src="nj">
    <lg>
      <l pos="pron">guhtet guoibmámet</l>
         <analysis>Pron_Recipr_Pl1_Acc</analysis>
         <analysis>Pron_Recipr_Pl1_Gen</analysis>
         <mini_paradigm>
            <analysis ms="Pron_Recipr_Pl1_Ill">
               <wordform>guhtet guoibmáseamet</wordform>
            </analysis>
            <analysis ms="Pron_Recipr_Pl1_Loc">
               <wordform>guhtet guoimmisteamet</wordform>
            </analysis>
            <analysis ms="Pron_Recipr_Pl1_Com">
               <wordform>guhtet guimmiineamet</wordform>
            </analysis>
         </mini_paradigm>
    </lg>
    <mg>
      <tg>
        <t pos="pron">hverandre (vi - flere enn 2)</t>
	   <xg>
          <x>mii dovdat guhtet guoibmámet</x>
          <xt>vi kjenner hverandre</xt>
        </xg>   
      </tg>
    </mg>
  </e>
  <e src="nj">
    <lg>
      <l pos="pron">guhtet guimmiideamet</l>
         <analysis>Pron_Recipr_Pl1_Acc</analysis>
         <analysis>Pron_Recipr_Pl1_Gen</analysis>
         <mini_paradigm>
            <analysis ms="Pron_Recipr_Pl1_Ill">
               <wordform>guhtet guimmiidasamet</wordform>
            </analysis>
            <analysis ms="Pron_Recipr_Pl1_Loc">
               <wordform>guhtet guimmiineamet</wordform>
            </analysis>
            <analysis ms="Pron_Recipr_Pl1_Com">
               <wordform>guhtet guimmiideametguin</wordform>
            </analysis>
         </mini_paradigm>
    </lg>
    <mg>
      <tg>
        <t pos="pron">hverandre (vi - flere enn 2)</t>
	   <xg>
          <x>mii dovdat guhtet guimmiideamet</x>
          <xt>vi kjenner hverandre</xt>
        </xg>   
      </tg>
    </mg>
  </e>


  <e src="nj">
    <lg>
      <l pos="pron">guhtet guoimmádet</l>
         <analysis>Pron_Recipr_Pl2_Acc</analysis>
         <analysis>Pron_Recipr_Pl2_Gen</analysis>
         <mini_paradigm>
            <analysis ms="Pron_Recipr_Pl2_Ill">
               <wordform>guhtet guoibmáseattet</wordform>
            </analysis>
            <analysis ms="Pron_Recipr_Pl2_Loc">
               <wordform>guhtet guoimmisteattet</wordform>
            </analysis>
            <analysis ms="Pron_Recipr_Pl2_Com">
               <wordform>guhtet guimmiineattet</wordform>
            </analysis>
         </mini_paradigm>
    </lg>
    <mg>
      <tg>
        <t pos="pron">hverandre (dere - flere enn 2)</t>
	   <xg>
          <x>dii dovdabehtet guhtet guoimmádet</x>
          <xt>dere kjenner hverandre</xt>
        </xg>   
      </tg>
    </mg>
  </e>
  <e src="nj">
    <lg>
      <l pos="pron">guhtet guimmiideattet</l>
         <analysis>Pron_Recipr_Pl2_Acc</analysis>
         <analysis>Pron_Recipr_Pl2_Gen</analysis>
         <mini_paradigm>
            <analysis ms="Pron_Recipr_Pl2_Ill">
               <wordform>guhtet guimmiidasadet</wordform>
            </analysis>
            <analysis ms="Pron_Recipr_Pl2_Loc">
               <wordform>guhtet guimmiineattet</wordform>
            </analysis>
            <analysis ms="Pron_Recipr_Pl2_Com">
               <wordform>guhtet guimmiideattetguin</wordform>
            </analysis>
         </mini_paradigm>
    </lg>
    <mg>
      <tg>
        <t pos="pron">hverandre (dere - flere enn 2)</t>
	   <xg>
          <x>dii dovdabehtet guhtet guimmiideattet</x>
          <xt>dere kjenner hverandre</xt>
        </xg>   
      </tg>
    </mg>
  </e>

  <e src="nj">
    <lg>
      <l pos="pron">guhtet guoimmiset</l>
         <analysis>Pron_Recipr_Pl3_Acc</analysis>
         <analysis>Pron_Recipr_Pl3_Gen</analysis>
         <mini_paradigm>
            <analysis ms="Pron_Recipr_Pl3_Ill">
               <wordform>guhtet guoibmáseaset</wordform>
            </analysis>
            <analysis ms="Pron_Recipr_Pl3_Loc">
               <wordform>guhtet guoimmisteaset</wordform>
            </analysis>
            <analysis ms="Pron_Recipr_Pl3_Com">
               <wordform>guhtet guimmiineaset</wordform>
            </analysis>
         </mini_paradigm>
    </lg>
    <mg>
      <tg>
        <t pos="pron">hverandre (de - flere enn 2)</t>
	   <xg>
          <x>sii dovdet guhtet guoimmiset</x>
          <xt>de kjenner hverandre</xt>
        </xg>   
      </tg>
    </mg>
  </e>
  <e src="nj">
    <lg>
      <l pos="pron">guhtet guimmiideaset</l>
         <analysis>Pron_Recipr_Pl3_Acc</analysis>
         <analysis>Pron_Recipr_Pl3_Gen</analysis>
         <mini_paradigm>
            <analysis ms="Pron_Recipr_Pl3_Ill">
               <wordform>guhtet guimmiidasaset</wordform>
            </analysis>
            <analysis ms="Pron_Recipr_Pl3_Loc">
               <wordform>guhtet guimmiineaset</wordform>
            </analysis>
            <analysis ms="Pron_Recipr_Pl3_Com">
               <wordform>guhtet guimmiideasetguin</wordform>
            </analysis>
         </mini_paradigm>
    </lg>
    <mg>
      <tg>
        <t pos="pron">hverandre (de - flere enn 2)</t>
	   <xg>
          <x>sii dovdet guhtet guimmiideaset</x>
          <xt>de kjenner hverandre</xt>
        </xg>   
      </tg>
    </mg>
  </e>

  <e src="nj">
    <lg>
      <l pos="pron">nubbi nuppi</l>
         <analysis>Pron_Recipr_Du_Acc</analysis>
         <analysis>Pron_Recipr_Du_Gen</analysis>
         <mini_paradigm>
            <analysis ms="Pron_Recipr_Du_Ill">
               <wordform>nubbi nubbái</wordform>
            </analysis>
            <analysis ms="Pron_Recipr_Du_Loc">
               <wordform>nubbi nuppis</wordform>
            </analysis>
            <analysis ms="Pron_Recipr_Du_Com">
               <wordform>nubbi nuppiin</wordform>
            </analysis>
            <analysis ms="Pron_Recipr_Du_Ess">
               <wordform>nubbi nubbin</wordform>
            </analysis>
         </mini_paradigm>
    </lg>
    <mg>
      <tg>
        <t pos="pron">hverandre (om to)</t>
	   <xg>
          <x>moai dovde nubbi nuppi</x>
          <xt>vi to kjenner hverandre</xt>
        </xg>   
      </tg>
    </mg>
  </e>
  <e src="nj">
    <lg>
      <l pos="pron">nuppit nuppiid</l>
         <analysis>Pron_Recipr_Pl_Acc</analysis>
         <analysis>Pron_Recipr_Pl_Gen</analysis>
         <mini_paradigm>
            <analysis ms="Pron_Recipr_Pl_Ill">
               <wordform>nuppit nuppiide</wordform>
            </analysis>
            <analysis ms="Pron_Recipr_Pl_Loc">
               <wordform>nuppit nuppiin</wordform>
            </analysis>
            <analysis ms="Pron_Recipr_Pl_Com">
               <wordform>nuppit nuppiiguin</wordform>
            </analysis>
            <analysis ms="Pron_Recipr_Pl_Ess">
               <wordform>nuppit nubbin</wordform>
            </analysis>
         </mini_paradigm>
    </lg>
    <mg>
      <tg>
        <t pos="pron">hverandre (flere enn to)</t>
	   <xg>
          <x>sii dovdet nuppit nuppiid</x>
          <xt>de kjenner hverandre</xt>
        </xg>   
      </tg>
    </mg>
  </e>


   <e>
      <lg>
         <l pos="pron">goabbat guoibmáseame</l>
         <lemma_ref>goabbat guoibmáme</lemma_ref>
         <analysis>Pron_Recipr_Du1_Ill</analysis>
      </lg>
      <mg>
         <tg>
            <t pos="pron">til hverandre (vi to)</t>
	   <xg>
          <x>moai muitaletne ságaid goabbat guoibmáseame</x>
          <xt>vi (to) forteller nytt til hverandre</xt>
        </xg>   
         </tg>
      </mg>
   </e>
   <e>
      <lg>
         <l pos="pron">goabbat guoimmisteame</l>
         <lemma_ref>goabbat guoibmáme</lemma_ref>
         <analysis>Pron_Recipr_Du1_Loc</analysis>
      </lg>
      <mg>
         <tg>
            <t pos="pron">hos hverandre (vi to)</t>
            <t pos="pron">fra hverandre (vi to)</t>
	   <xg>
          <x>moai ožžo rávvagiid goabbat guoimmisteame</x>
          <xt>vi (to) får råd fra hverandre</xt>
        </xg>   
         </tg>
      </mg>
   </e>
   <e>
      <lg>
         <l pos="pron">goabbat guimmiineame</l>
         <lemma_ref>goabbat guoibmáme</lemma_ref>
         <analysis>Pron_Recipr_Du1_Com</analysis>
      </lg>
      <mg>
         <tg>
            <t pos="pron">med hverandre (vi to)</t>
	   <xg>
          <x>moai leaikkastalle goabbat guimmiineame</x>
          <xt>vi (to) spøker med hverandre</xt>
        </xg>   
         </tg>
      </mg>
   </e>
   <e>
      <lg>
         <l pos="pron">goabbat guoibmáseatte</l>
         <lemma_ref>goabbat guoimmáde</lemma_ref>
         <analysis>Pron_Recipr_Du2_Ill</analysis>
      </lg>
      <mg>
         <tg>
            <t pos="pron">til hverandre (dere to)</t>
	   <xg>
          <x>doai muitaleahppi ságaid goabbat guoibmáseatte</x>
          <xt>dere (to) forteller nytt til hverandre</xt>
        </xg>   
         </tg>
      </mg>
   </e>
   <e>
      <lg>
         <l pos="pron">goabbat guoimmisteatte</l>
         <lemma_ref>goabbat guoimmáde</lemma_ref>
         <analysis>Pron_Recipr_Du2_Loc</analysis>
      </lg>
      <mg>
         <tg>
            <t pos="pron">fra hverandre (dere to)</t>
	   <xg>
          <x>doai oažžubeahtti rávvagiid goabbat guoimmisteatte</x>
          <xt>dere (to) får råd fra hverandre</xt>
        </xg>   
         </tg>
      </mg>
   </e>
   <e>
      <lg>
         <l pos="pron">goabbat guimmiineatte</l>
         <lemma_ref>goabbat guoimmáde</lemma_ref>
         <analysis>Pron_Recipr_Du2_Com</analysis>
      </lg>
      <mg>
         <tg>
            <t pos="pron">med hverandre (dere to)</t>
	   <xg>
          <x>doai leaikkastallabeahtti goabbat guimmiineatte</x>
          <xt>dere (to) spøker med hverandre</xt>
        </xg>   
         </tg>
      </mg>
   </e>
   <e>
      <lg>
         <l pos="pron">goabbat guoibmáseaskka</l>
         <lemma_ref>goabbat guoimmiska</lemma_ref>
         <analysis>Pron_Recipr_Du3_Ill</analysis>
      </lg>
      <mg>
         <tg>
            <t pos="pron">til hverandre (de to)</t>
	   <xg>
          <x>soai muitaleaba ságaid goabbat guoibmáseaskka</x>
          <xt>de (to) forteller nytt til hverandre</xt>
        </xg>   
         </tg>
      </mg>
   </e>
   <e>
      <lg>
         <l pos="pron">goabbat guoimmisteaskka</l>
         <lemma_ref>goabbat guoimmiska</lemma_ref>
         <analysis>Pron_Recipr_Du3_Loc</analysis>
      </lg>
      <mg>
         <tg>
            <t pos="pron">hos hverandre (de to)</t>
            <t pos="pron">fra hverandre (de to)</t>
	   <xg>
          <x>soai oažžuba rávvagiid goabbat guoimmisteaskka</x>
          <xt>de (to) får råd fra hverandre</xt>
        </xg>   
         </tg>
      </mg>
   </e>
   <e>
      <lg>
         <l pos="pron">goabbat guimmiineaskka</l>
         <lemma_ref>goabbat guoimmiska</lemma_ref>
         <analysis>Pron_Recipr_Du3_Com</analysis>
      </lg>
      <mg>
         <tg>
            <t pos="pron">med hverandre (de to)</t>
	   <xg>
          <x>soai leaikkastallaba goabbat guimmiineaskka</x>
          <xt>de (to) spøker med hverandre</xt>
        </xg>   
         </tg>
      </mg>
   </e>
   <e>
      <lg>
         <l pos="pron">guhtet guoibmáseamet</l>
         <lemma_ref>guhtet guoibmámet</lemma_ref>
         <analysis>Pron_Recipr_Pl1_Ill</analysis>
      </lg>
      <mg>
         <tg>
            <t pos="pron">til hverandre (vi)</t>
	   <xg>
          <x>mii muitalit ságaid guhtet guoibmáseamet</x>
          <xt>vi forteller nytt til hverandre</xt>
        </xg>   
         </tg>
      </mg>
   </e>
   <e>
      <lg>
         <l pos="pron">guhtet guoimmisteamet</l>
         <lemma_ref>guhtet guoibmámet</lemma_ref>
         <analysis>Pron_Recipr_Pl1_Loc</analysis>
      </lg>
      <mg>
         <tg>
            <t pos="pron">hos hverandre (vi)</t>
            <t pos="pron">fra hverandre (vi)</t>
	   <xg>
          <x>mii oažžut rávvagiid guhtet guoimmisteamet</x>
          <xt>vi får råd fra hverandre</xt>
        </xg>   
         </tg>
      </mg>
   </e>
   <e>
      <lg>
         <l pos="pron">guhtet guimmiineamet</l>
         <lemma_ref>guhtet guoibmámet</lemma_ref>
         <analysis>Pron_Recipr_Pl1_Com</analysis>
      </lg>
      <mg>
         <tg>
            <t pos="pron">med hverandre (vi)</t>
	   <xg>
          <x>mii leaikkastallat guhtet guimmiineamet</x>
          <xt>vi skøyer med hverandre</xt>
        </xg>   
         </tg>
      </mg>
   </e>

   <e>
      <lg>
         <l pos="pron">guhtet guimmiidasamet</l>
         <lemma_ref>guhtet guimmiideamet</lemma_ref>
         <analysis>Pron_Recipr_Pl1_Ill</analysis>
      </lg>
      <mg>
         <tg>
            <t pos="pron">til hverandre (vi)</t>
	   <xg>
          <x>mii muitalit ságaid guhtet guimmiidasamet</x>
          <xt>vi forteller nytt til hverandre</xt>
        </xg>   
         </tg>
      </mg>
   </e>
   <e>
      <lg>
         <l pos="pron">guhtet guimmiineamet</l>
         <lemma_ref>guhtet guimmiideamet</lemma_ref>
         <analysis>Pron_Recipr_Pl1_Loc</analysis>
      </lg>
      <mg>
         <tg>
            <t pos="pron">hos hverandre (vi)</t>
            <t pos="pron">fra hverandre (vi)</t>
	   <xg>
          <x>mii oažžut rávvagiid guhtet guimmiineamet</x>
          <xt>vi får råd fra hverandre</xt>
        </xg>   
         </tg>
      </mg>
   </e>
   <e>
      <lg>
         <l pos="pron">guhtet guimmiideametguin</l>
         <lemma_ref>guhtet guimmiideamet</lemma_ref>
         <analysis>Pron_Recipr_Pl1_Com</analysis>
      </lg>
      <mg>
         <tg>
            <t pos="pron">med hverandre (vi)</t>
	   <xg>
          <x>mii leaikkastallat guhtet guimmiideametguin</x>
          <xt>vi skøyer med hverandre</xt>
        </xg>   
         </tg>
      </mg>
   </e>

   <e>
      <lg>
         <l pos="pron">guhtet guoibmáseattet</l>
         <lemma_ref>guhtet guoimmádet</lemma_ref>
         <analysis>Pron_Recipr_Pl2_Ill</analysis>
      </lg>
      <mg>
         <tg>
            <t pos="pron">til hverandre (dere)</t>
	   <xg>
          <x>dii muitalehpet ságaid guhtet guoibmáseattet</x>
          <xt>dere forteller nytt til hverandre</xt>
        </xg>   
         </tg>
      </mg>
   </e>
   <e>
      <lg>
         <l pos="pron">guhtet guoimmisteattet</l>
         <lemma_ref>guhtet guoimmádet</lemma_ref>
         <analysis>Pron_Recipr_Pl2_Loc</analysis>
      </lg>
      <mg>
         <tg>
            <t pos="pron">hos hverandre (dere)</t>
            <t pos="pron">fra hverandre (dere)</t>
	   <xg>
          <x>dii oažžubehtet rávvagiid guhtet guoimmisteattet</x>
          <xt>dere får råd fra hverandre</xt>
        </xg>   
         </tg>
      </mg>
   </e>
   <e>
      <lg>
         <l pos="pron">guhtet guimmiineattet</l>
         <lemma_ref>guhtet guoimmádet</lemma_ref>
         <analysis>Pron_Recipr_Pl2_Com</analysis>
      </lg>
      <mg>
         <tg>
            <t pos="pron">med hverandre (dere)</t>
	   <xg>
          <x>dii leaikkastallabehtet guhtet guimmiineattet</x>
          <xt>dere skøyer med hverandre</xt>
        </xg>   
         </tg>
      </mg>
   </e>

   <e>
      <lg>
         <l pos="pron">guhtet guimmiidasadet</l>
         <lemma_ref>guhtet guimmiideattet</lemma_ref>
         <analysis>Pron_Recipr_Pl2_Ill</analysis>
      </lg>
      <mg>
         <tg>
            <t pos="pron">til hverandre (dere)</t>
	   <xg>
          <x>dii muitalehpet ságaid guhtet guimmiidasadet</x>
          <xt>dere forteller nytt til hverandre</xt>
        </xg>   
         </tg>
      </mg>
   </e>
   <e>
      <lg>
         <l pos="pron">guhtet guimmiineattet</l>
         <lemma_ref>guhtet guimmiideattet</lemma_ref>
         <analysis>Pron_Recipr_Pl2_Loc</analysis>
      </lg>
      <mg>
         <tg>
            <t pos="pron">hos hverandre (dere)</t>
            <t pos="pron">fra hverandre (dere)</t>
	   <xg>
          <x>dii oažžubehtet rávvagiid guhtet guimmiineattet</x>
          <xt>dere får råd fra hverandre</xt>
        </xg>   
         </tg>
      </mg>
   </e>
   <e>
      <lg>
         <l pos="pron">guhtet guimmiideattetguin</l>
         <lemma_ref>guhtet guimmiideattet</lemma_ref>
         <analysis>Pron_Recipr_Pl2_Com</analysis>
      </lg>
      <mg>
         <tg>
            <t pos="pron">med hverandre (dere)</t>
	   <xg>
          <x>dii leaikkastallabehtet guhtet guimmiideattetguin</x>
          <xt>dere skøyer med hverandre</xt>
        </xg>   
         </tg>
      </mg>
   </e>

   <e>
      <lg>
         <l pos="pron">guhtet guoibmáseaset</l>
         <lemma_ref>guhtet guoimmiset</lemma_ref>
         <analysis>Pron_Recipr_Pl3_Ill</analysis>
      </lg>
      <mg>
         <tg>
            <t pos="pron">til hverandre (de)</t>
	   <xg>
          <x>sii muitalit ságaid guhtet guoibmáseaset</x>
          <xt>de forteller nytt til hverandre</xt>
        </xg>   
         </tg>
      </mg>
   </e>
   <e>
      <lg>
         <l pos="pron">guhtet guoimmisteaset</l>
         <lemma_ref>guhtet guoimmiset</lemma_ref>
         <analysis>Pron_Recipr_Pl3_Loc</analysis>
      </lg>
      <mg>
         <tg>
            <t pos="pron">hos hverandre (de)</t>
            <t pos="pron">fra hverandre (de)</t>
	   <xg>
          <x>sii ožžot rávvagiid guhtet guoimmisteaset</x>
          <xt>de får råd fra hverandre</xt>
        </xg>   
         </tg>
      </mg>
   </e>
   <e>
      <lg>
         <l pos="pron">guhtet guimmiineaset</l>
         <lemma_ref>guhtet guoimmiset</lemma_ref>
         <analysis>Pron_Recipr_Pl3_Com</analysis>
      </lg>
      <mg>
         <tg>
            <t pos="pron">med hverandre (de)</t>
	   <xg>
          <x>sii leaikkastallet guhtet guimmiineaset</x>
          <xt>de skøyer med hverandre</xt>
        </xg>   
         </tg>
      </mg>
   </e>

   <e>
      <lg>
         <l pos="pron">guhtet guimmiidasaset</l>
         <lemma_ref>guhtet guimmiideaset</lemma_ref>
         <analysis>Pron_Recipr_Pl3_Ill</analysis>
      </lg>
      <mg>
         <tg>
            <t pos="pron">til hverandre (de)</t>
	   <xg>
          <x>sii muitalit ságaid guhtet guimmiidasaset</x>
          <xt>de forteller nytt til hverandre</xt>
        </xg>   
         </tg>
      </mg>
   </e>
   <e>
      <lg>
         <l pos="pron">guhtet guimmiineaset</l>
         <lemma_ref>guhtet guimmiideaset</lemma_ref>
         <analysis>Pron_Recipr_Pl3_Loc</analysis>
      </lg>
      <mg>
         <tg>
            <t pos="pron">hos hverandre (de)</t>
            <t pos="pron">fra hverandre (de)</t>
	   <xg>
          <x>sii ožžot rávvagiid guhtet guimmiineaset</x>
          <xt>de får råd fra hverandre</xt>
        </xg>   
         </tg>
      </mg>
   </e>
   <e>
      <lg>
         <l pos="pron">guhtet guimmiideasetguin</l>
         <lemma_ref>guhtet guimmiideaset</lemma_ref>
         <analysis>Pron_Recipr_Pl3_Com</analysis>
      </lg>
      <mg>
         <tg>
            <t pos="pron">med hverandre (de)</t>
	   <xg>
          <x>sii leaikkastallet guhtet guimmiideasetguin</x>
          <xt>de skøyer med hverandre</xt>
        </xg>   
         </tg>
      </mg>
   </e>
   <e>
      <lg>
         <l pos="pron">nubbi nubbái</l>
         <lemma_ref>nubbi nuppi</lemma_ref>
         <analysis>Pron_Recipr_Du_Ill</analysis>
      </lg>
      <mg>
         <tg>
            <t pos="pron">til hverandre (om to)</t>
	   <xg>
          <x>soai muitaleaba ságaid nubbi nubbái</x>
          <xt>de to forteller nytt til hverandre</xt>
        </xg>   
         </tg>
      </mg>
   </e>
   <e>
      <lg>
         <l pos="pron">nubbi nuppis</l>
         <lemma_ref>nubbi nuppi</lemma_ref>
         <analysis>Pron_Recipr_Du_Loc</analysis>
      </lg>
      <mg>
         <tg>
            <t pos="pron">hos hverandre (om to)</t>
            <t pos="pron">fra hverandre (om to)</t>
	   <xg>
          <x>soai oažžuba rávvagiid nubbi nuppis</x>
          <xt>de to får råd fra hverandre</xt>
        </xg>   
         </tg>
      </mg>
   </e>
   <e>
      <lg>
         <l pos="pron">nubbi nuppiin</l>
         <lemma_ref>nubbi nuppi</lemma_ref>
         <analysis>Pron_Recipr_Du_Com</analysis>
      </lg>
      <mg>
         <tg>
            <t pos="pron">med hverandre (om to)</t>
	   <xg>
          <x>soai leaikastallaba nubbi nuppiin</x>
          <xt>de to spøker med hverandre</xt>
        </xg>   
         </tg>
      </mg>
   </e>
   <e>
      <lg>
         <l pos="pron">nubbi nubbin</l>
         <lemma_ref>nubbi nuppi</lemma_ref>
         <analysis>Pron_Recipr_Du_Ess</analysis>
      </lg>
      <mg>
         <tg>
            <t pos="pron">som hverandre (om to)</t> 
	   <xg>
          <x>soai loggiiga sisa nubbi nubbin</x>
          <xt>de to logget inn som hverandre</xt>
        </xg>   
         </tg>
      </mg>
   </e>
   <e>
      <lg>
         <l pos="pron">nuppit nuppiide</l>
         <lemma_ref>nuppit nuppiid</lemma_ref>
         <analysis>Pron_Recipr_Pl_Ill</analysis>
      </lg>
      <mg>
         <tg>
            <t pos="pron">til hverandre (om flere enn to)</t>
	   <xg>
          <x>sii muitalit ságaid nuppit nuppiide</x>
          <xt>de forteller nytt til hverandre</xt>
        </xg>   
         </tg>
      </mg>
   </e>
   <e>
      <lg>
         <l pos="pron">nuppit nuppiin</l>
         <lemma_ref>nuppit nuppiid</lemma_ref>
         <analysis>Pron_Recipr_Pl_Loc</analysis>
      </lg>
      <mg>
         <tg>
            <t pos="pron">hos hverandre (om flere enn to)</t>
            <t pos="pron">fra hverandre (om flere enn to)</t>
	   <xg>
          <x>mii oažžut rávvagiid nuppit nuppiin</x>
          <xt>vi får råd fra hverandre</xt>
        </xg>   
         </tg>
      </mg>
   </e>
   <e>
      <lg>
         <l pos="pron">nuppit nuppiiguin</l>
         <lemma_ref>nuppit nuppiid</lemma_ref>
         <analysis>Pron_Recipr_Pl_Com</analysis>
      </lg>
      <mg>
         <tg>
            <t pos="pron">med hverandre (om flere enn to)</t>
	   <xg>
          <x>dii leaikastallabehtet nuppit nuppiiguin</x>
          <xt>dere spøker med hverandre</xt>
        </xg>   
         </tg>
      </mg>
   </e>
   <e>
      <lg>
         <l pos="pron">nuppit nubbin</l>
         <lemma_ref>nuppit nuppiid</lemma_ref>
         <analysis>Pron_Recipr_Du_Ess</analysis>
      </lg>
      <mg>
         <tg>
            <t pos="pron">som hverandre (om flere enn to)</t>
        </tg>
      </mg>
   </e>

</r>
